{
  "feature.app.serverException.message.text": "Oops, Something went wrong!<br />Please try again later",
  "feature.app.uiException.message.text": "Oops, Something went wrong!<br />Please refresh manually or try again later",

  "feature.loginPage.alert.incorrectInfo.message": "Incorrect username or password!!",
  "feature.loginPage.alert.compulsoryInfo.message": "Both <b>username</b> & <b>password</b> are mandatory!!",

  "feature.common.loader.uploadProgress.message": "{{percentCompleted}}% items fetched ...",
  "feature.common.loader.processing.message": "Processing ...",

  "features.purchaseScreenMessages.resetPurchaseConfirmation": "Are you sure you want to reset the purchase?",

  "features.purchaseScreenMessages.draftDialogTitle": "View Drafts",
  "features.purchaseScreenMessages.totalAmountLabel": "Total Amount : Rs.",
  "features.purchaseScreenMessages.itemDetail": "Item Detail",
  "features.purchaseScreenMessages.quantity": "Quantity",
  "features.purchaseScreenMessages.purchasePrice": "Purchase Price",
  "features.purchaseScreenMessages.sellingPrice": "Selling Price",
  "features.purchaseScreenMessages.total": "Total",
  "features.purchaseScreenMessages.action": "Action",
  "features.purchaseScreenMessages.paymentMode": "Payment Method",
  "features.purchaseScreenMessages.cash": "Cash",
  "features.purchaseScreenMessages.card": "Card",
  "features.purchaseScreenMessages.upi": "UPI",
  "features.purchaseScreenMessages.draftsTitle": "Drafts",
  "features.purchaseScreenMessages.selectDraftMessage": "Select a draft to load or delete it.",

  "feature.common.templates.loadingMessage.text": "Loading ...",
  "feature.common.templates.popups.errorHeading.text": "Error",
  "feature.common.templates.popups.info.dontShowAgain.text": "Do not show this again",
  "feature.common.templates.popups.general.close.button": "Close",
  "feature.common.templates.popups.general.cancel.button": "Cancel",
  "feature.common.templates.popups.general.confirmation.button": "Confirmation",
  "feature.common.templates.popups.general.delete.button": "Delete",
  "feature.common.templates.popups.general.yes.button": "Yes",
  "feature.common.templates.popups.general.apply.button": "Apply",
  "feature.common.templates.popups.general.saveAndClose.button": "Save & Close"
}
