{
  "feature.app.serverException.message.text": "Oops, Something went wrong!<br />Please try again later",
  "feature.app.uiException.message.text": "Oops, Something went wrong!<br />Please refresh manually or try again later",
  "feature.app.resetConfirmation.text": "Are you sure you want to reset?",

  "feature.loginPage.alert.incorrectInfo.message": "Incorrect username or password!!",
  "feature.loginPage.alert.compulsoryInfo.message": "Both <b>username</b> & <b>password</b> are mandatory!!",

  "feature.salesScreen.salesOrderTitle": "Sales Order",
  "feature.salesScreen.viewDrafts": "View Drafts",
  "feature.salesScreen.customerNameLabel": "Customer's Name",
  "feature.salesScreen.salesOrderDateLabel": "Sales Order Date",
  "feature.salesScreen.addItemButton": "Add Item",
  "feature.salesScreen.paymentModeLabel": "Payment Mode",
  "feature.salesScreen.discountTypeLabel": "Discount Type",
  "feature.salesScreen.discountValueLabel": {
    "percentage": "Percentage (%)",
    "absolute": "Absolute (Rs.)"
  },
  "feature.salesScreen.paidAmountLabel": "Paid Amount",
  "feature.salesScreen.totalAmountLabel": "Total Amount : Rs.",
  "feature.salesScreen.printBillButton": "Print Bill",
  "feature.salesScreen.resetButton": "Reset",
  "feature.salesScreen.saveDraftButton": "Save as Draft",
  "feature.salesScreen.confirmButton": "Confirm",
  "feature.salesScreen.resetConfirmationTitle": "Confirmation",
  "feature.salesScreen.resetConfirmationMessage": "Are you sure you want to reset the Order?",
  "feature.salesScreen.draftsTitle": "Drafts",
  "feature.salesScreen.selectDraftMessage": "Select a draft to load or delete it.",
  "feature.salesScreen.itemDetailColumnName": "Item Detail",
  "feature.salesScreen.quantityColumnName": "Quantity",
  "feature.salesScreen.rateColumnName": "Rate",
  "feature.salesScreen.totalColumnName": "Total",
  "feature.salesScreen.actionColumnName": "Action",

  "feature.common.loader.uploadProgress.message": "{{percentCompleted}}% items fetched ...",
  "feature.common.loader.processing.message": "Processing ...",

  "feature.common.templates.loadingMessage.text": "Loading ...",
  "feature.common.templates.popups.errorHeading.text": "Error",
  "feature.common.templates.popups.info.dontShowAgain.text": "Do not show this again",
  "feature.common.templates.popups.general.close.button": "Close",
  "feature.common.templates.popups.general.cancel.button": "Cancel",
  "feature.common.templates.popups.general.delete.button": "Delete",
  "feature.common.templates.popups.general.yes.button": "Yes",
  "feature.common.templates.popups.general.apply.button": "Apply",
  "feature.common.templates.popups.general.saveAndClose.button": "Save & Close"
}
